telebirrweb
